mass_iq/__init__.py
mass_iq/client/Client.py
mass_iq/client/__init__.py
mass_iq/client/aio/Client.py
mass_iq/client/aio/__init__.py
mass_iq/config/__init__.py
mass_iq/config/config.py
mass_iq/resources/latest/openapi.json
mass_iq-1.0.0.dist-info/METADATA
mass_iq-1.0.0.dist-info/WHEEL
mass_iq-1.0.0.dist-info/RECORD
