Metadata-Version: 2.4
Name: mass-iq
Version: 1.0.0
Summary: Client package to interact with the massIQ API
License: MIT
Author: Jannick Kappelmann
Author-email: jannick.kappelmann@gmail.com
Requires-Python: >=3.12,<4.0
Classifier: License :: OSI Approved :: MIT License
Classifier: Programming Language :: Python :: 3
Classifier: Programming Language :: Python :: 3.12
Classifier: Programming Language :: Python :: 3.13
Classifier: Programming Language :: Python :: 3.14
Requires-Dist: aiohttp (==3.12.15)
Requires-Dist: cachetools (==5.5.2)
Requires-Dist: pydantic-settings (>=2.10.1,<3.0.0)
Requires-Dist: requests (==2.32.4)
Requires-Dist: tenacity (==8.5.0)
Project-URL: Homepage, https://github.com/jannickk/mass-iq
